brioche/__init__.py
brioche/biomization.py
brioche/helpers.py
brioche/mappings.py
brioche/samples.py
brioche/tool.py
brioche-1.0.0.dist-info/entry_points.txt
brioche-1.0.0.dist-info/LICENSE
brioche-1.0.0.dist-info/WHEEL
brioche-1.0.0.dist-info/METADATA
brioche-1.0.0.dist-info/RECORD
